{"title":{"a":"Lista/Pacto","b":"Partido","c":"Votos","d":"Porcentaje","e":"Candidatos","f":"Electo","sd":null},"isVisible":{"a":"true","b":"true","c":"true","d":"true","e":"false","f":"true","sd":null},"dataType":{"a":"String","b":"String","c":"Integer","d":"Integer","e":"Integer","f":"Integer","sd":null},"data":[{"a":"A. CHILE VAMOS UDI - PRI - INDEPENDIENTES","b":null,"c":"267","d":"3,64%","e":"3","f":"","sd":[{"a":"SUBPACTO UDI - INDEPENDIENTES","b":null,"c":"267","d":"3,64%","e":null,"f":null,"sd":[{"a":"110. FEDERICO KRUGER FINSTERBUSCH","b":"UDI","c":"110","d":"1,50%","e":null,"f":"*","sd":null},{"a":"111. SERAFIN ALTAMIRANO GARRIDO","b":"UDI","c":"72","d":"0,98%","e":null,"f":"","sd":null},{"a":"112. MARCOS VELASQUEZ MACIAS","b":"IND","c":"85","d":"1,16%","e":null,"f":"","sd":null}]}]},{"a":"B. POR TODO CHILE","b":null,"c":"173","d":"2,36%","e":"3","f":"","sd":[{"a":"SUBPACTO PRO + INDEPENDIENTES","b":null,"c":"173","d":"2,36%","e":null,"f":null,"sd":[{"a":"113. RICARDO ALBERTO BARRIENTOS TECA","b":"PRO","c":"97","d":"1,32%","e":null,"f":"","sd":null},{"a":"114. ENZO PATRICIO ROJEL BARRIENTOS","b":"PRO","c":"34","d":"0,46%","e":null,"f":"","sd":null},{"a":"115. ANDRES  CAMUS BADILLO","b":"IND","c":"42","d":"0,57%","e":null,"f":"","sd":null}]}]},{"a":"E. CHILE VAMOS RN - EVOPOLI","b":null,"c":"3.621","d":"49,33%","e":"4","f":"","sd":[{"a":"SUBPACTO RN - INDEPENDIENTES","b":null,"c":"3.621","d":"49,33%","e":null,"f":null,"sd":[{"a":"116. FERNANDO BORQUEZ MONTECINOS","b":"RN","c":"138","d":"1,88%","e":null,"f":"*","sd":null},{"a":"117. FRANCISCO  CARCAMO HERNANDEZ","b":"RN","c":"3.174","d":"43,24%","e":null,"f":"","sd":null},{"a":"118. JUANA  CARDENAS VEGA","b":"RN","c":"255","d":"3,47%","e":null,"f":"","sd":null},{"a":"119. JULIO SANZANA CARDENAS","b":"IND","c":"54","d":"0,74%","e":null,"f":"","sd":null}]}]},{"a":"F. POR UN CHILE JUSTO Y DESCENTRALIZADO","b":null,"c":"2.083","d":"28,37%","e":"4","f":"","sd":[{"a":"SUBPACTO PCCH E INDEPENDIENTES","b":null,"c":"700","d":"9,54%","e":null,"f":null,"sd":[{"a":"120. MARIO ENRIQUE CONTRERAS VEGA","b":"PCCH","c":"103","d":"1,40%","e":null,"f":"","sd":null},{"a":"121. ANA MAGDALENA VERA ARANCIBIA","b":"PCCH","c":"597","d":"8,13%","e":null,"f":"","sd":null}]},{"a":"SUBPACTO PPD E INDEPENDIENTES","b":null,"c":"1.383","d":"18,84%","e":null,"f":null,"sd":[{"a":"122. CRISTIAN ESTEBAN MIRANDA BORQUEZ","b":"PPD","c":"1.345","d":"18,32%","e":null,"f":"*","sd":null},{"a":"123. RUBEN PATRICIO FLORES CUEVAS","b":"IND","c":"38","d":"0,52%","e":null,"f":"","sd":null}]}]},{"a":"K. COALICIÓN REGIONALISTA VERDE","b":null,"c":"194","d":"2,64%","e":"4","f":"","sd":[{"a":"SUBPACTO DEMOCRACIA REGIONAL E INDEPENDIENTES","b":null,"c":"194","d":"2,64%","e":null,"f":null,"sd":[{"a":"124. RODRIGO ALEXIS RIVAL MORALES","b":"DRP","c":"75","d":"1,02%","e":null,"f":"","sd":null},{"a":"125. BENITO HERIBERTO PEREZ MUÑOZ","b":"DRP","c":"49","d":"0,67%","e":null,"f":"","sd":null},{"a":"126. INGRID JEANNETTE GUAQUIN GUAQUIN","b":"IND","c":"34","d":"0,46%","e":null,"f":"","sd":null},{"a":"127. ANGELICA DEL TRANSITO CALISTO CHAMBLA","b":"IND","c":"36","d":"0,49%","e":null,"f":"","sd":null}]}]},{"a":"L. UNIDOS POR LA DESCENTRALIZACION","b":null,"c":"845","d":"11,51%","e":"3","f":"","sd":[{"a":"SUBPACTO PDC E INDEPENDIENTES","b":null,"c":"646","d":"8,80%","e":null,"f":null,"sd":[{"a":"128. NELSON  AGUILA SERPA","b":"PDC","c":"382","d":"5,20%","e":null,"f":"*","sd":null},{"a":"129. MAURICIO HENRIQUEZ SANDOVAL","b":"PDC","c":"264","d":"3,60%","e":null,"f":"","sd":null}]},{"a":"SUBPACTO PS E INDEPENDIENTES","b":null,"c":"199","d":"2,71%","e":null,"f":null,"sd":[{"a":"130. MANUEL BALLESTEROS CURUMILLA","b":"PSCH","c":"199","d":"2,71%","e":null,"f":"","sd":null}]}]},{"a":"Q. FRENTE ECOLOGISTA Y CIUDADANO","b":null,"c":"158","d":"2,15%","e":"1","f":"","sd":[{"a":"131. MARCELA PAZ RAMOS ESPINOSA","b":"IND","c":"158","d":"2,15%","e":null,"f":"","sd":null}]}],"resumen":[{"a":"Válidamente Emitidos","b":null,"c":"7.341","d":"87,05%","e":null,"f":null,"sd":null},{"a":"Votos Nulos","b":null,"c":"304","d":"3,60%","e":null,"f":null,"sd":null},{"a":"Votos en Blanco","b":null,"c":"788","d":"9,34%","e":null,"f":null,"sd":null},{"a":"Total Votación","b":null,"c":"8.433","d":"100,00%","e":null,"f":null,"sd":null}],"colegioEscrutador":null,"labels":"4","mesasEscrutadas":"63","totalMesas":"63","totalMesasPorcent":"100,00%","tipoGlosaComputo":"1","mostrarGlosaNominados":true,"tipoGlosaNominados":null}