[{"c":1850081,"d":"81M","md":false},{"c":1850082,"d":"82M","md":false},{"c":1850083,"d":"83M","md":false},{"c":1850084,"d":"84M","md":false},{"c":1850085,"d":"85M","md":false},{"c":1850086,"d":"86M","md":false},{"c":1850087,"d":"87M","md":false},{"c":1850088,"d":"88M","md":false},{"c":1850089,"d":"89M","md":false},{"c":1850090,"d":"90M","md":false},{"c":1850091,"d":"91M","md":true},{"c":1850092,"d":"92M","md":false},{"c":1850093,"d":"93M","md":false},{"c":1850094,"d":"94M","md":true},{"c":1850095,"d":"95M","md":false},{"c":1850096,"d":"96M","md":false},{"c":1850097,"d":"97M","md":false},{"c":1850098,"d":"98M","md":false},{"c":1850099,"d":"99M","md":false},{"c":1850100,"d":"100M","md":false}]