[{"c":1440001,"d":"1M","md":false},{"c":1440002,"d":"2M","md":false},{"c":1440003,"d":"3M","md":false},{"c":1440004,"d":"4M","md":false},{"c":1440005,"d":"5M","md":false},{"c":1440006,"d":"6M","md":false},{"c":1440007,"d":"7M","md":false},{"c":1440008,"d":"8M","md":false},{"c":1440009,"d":"9M","md":false},{"c":1440010,"d":"10M","md":false},{"c":1440011,"d":"11M","md":false},{"c":1440012,"d":"12M","md":false},{"c":1440013,"d":"13M","md":false},{"c":1440014,"d":"14M","md":false},{"c":1440015,"d":"15M","md":false},{"c":1440016,"d":"16M","md":true},{"c":1440017,"d":"17M","md":false},{"c":1440018,"d":"18M","md":false},{"c":1440019,"d":"19M","md":false},{"c":1440020,"d":"20M","md":false},{"c":1440021,"d":"21M","md":false}]