[{"c":531077,"d":"77V","md":false},{"c":531078,"d":"78V","md":false},{"c":531079,"d":"79V","md":false},{"c":531080,"d":"80V","md":false},{"c":531081,"d":"81V","md":false},{"c":531082,"d":"82V","md":false},{"c":531083,"d":"83V","md":false},{"c":531084,"d":"84V","md":false},{"c":531085,"d":"85V","md":false},{"c":531086,"d":"86V","md":false},{"c":531087,"d":"87V","md":false},{"c":531088,"d":"88V","md":false},{"c":531089,"d":"89V","md":false},{"c":531090,"d":"90V","md":false},{"c":532095,"d":"95","md":false},{"c":532096,"d":"96","md":false},{"c":532097,"d":"97","md":false},{"c":532098,"d":"98","md":false},{"c":532099,"d":"99","md":false},{"c":532100,"d":"100","md":false},{"c":532101,"d":"101","md":false},{"c":532102,"d":"102","md":false}]