{"title":{"a":"Lista/Pacto","b":"Partido","c":"Votos","d":"Porcentaje","e":"Candidatos","f":"Electo","sd":null},"isVisible":{"a":"true","b":"true","c":"true","d":"true","e":"false","f":"true","sd":null},"dataType":{"a":"String","b":"String","c":"Integer","d":"Integer","e":"Integer","f":"Integer","sd":null},"data":[{"a":"A. CHILE VAMOS UDI - PRI - INDEPENDIENTES","b":null,"c":"665","d":"15,05%","e":"5","f":"","sd":[{"a":"SUBPACTO UDI - INDEPENDIENTES","b":null,"c":"525","d":"11,88%","e":null,"f":null,"sd":[{"a":"110. EDUARDO BORGOÑO BUSTOS","b":"UDI","c":"268","d":"6,07%","e":null,"f":"*","sd":null},{"a":"111. DANIEL IRAIRA SAGREDO","b":"IND","c":"71","d":"1,61%","e":null,"f":"","sd":null},{"a":"112. ENRIQUE KRAUSE LOBOS","b":"IND","c":"186","d":"4,21%","e":null,"f":"*","sd":null}]},{"a":"SUBPACTO PRI E INDEPENDIENTES","b":null,"c":"140","d":"3,17%","e":null,"f":null,"sd":[{"a":"113. CRISTIAN ANDRES FUENTES FUENTES","b":"PRI","c":"90","d":"2,04%","e":null,"f":"","sd":null},{"a":"114. JULIO ALEJANDRO CANO SAN MARTIN","b":"PRI","c":"50","d":"1,13%","e":null,"f":"","sd":null}]}]},{"a":"B. POR TODO CHILE","b":null,"c":"244","d":"5,52%","e":"3","f":"","sd":[{"a":"SUBPACTO PRO + INDEPENDIENTES","b":null,"c":"244","d":"5,52%","e":null,"f":null,"sd":[{"a":"115. CRISTIAN ANTONIO IBAÑEZ IBAÑEZ","b":"PRO","c":"95","d":"2,15%","e":null,"f":"","sd":null},{"a":"116. PEDRO ALFONSO BASTIDAS OLIVA","b":"PRO","c":"62","d":"1,40%","e":null,"f":"","sd":null},{"a":"117. RICARDO ALFREDO GIERKE CORREA","b":"IND","c":"87","d":"1,97%","e":null,"f":"","sd":null}]}]},{"a":"E. CHILE VAMOS RN - EVOPOLI","b":null,"c":"1.641","d":"37,14%","e":"5","f":"","sd":[{"a":"SUBPACTO RN - INDEPENDIENTES","b":null,"c":"1.477","d":"33,43%","e":null,"f":null,"sd":[{"a":"118. PATRICIO BADILLA COFRE","b":"RN","c":"1.222","d":"27,66%","e":null,"f":"*","sd":null},{"a":"119. JORGE LOPEZ FARIS","b":"RN","c":"181","d":"4,10%","e":null,"f":"","sd":null},{"a":"120. VLADIMIR FICA ESPINOZA","b":"IND","c":"74","d":"1,67%","e":null,"f":"","sd":null}]},{"a":"SUBPACTO EVOPOLI E INDEPENDIENTES","b":null,"c":"164","d":"3,71%","e":null,"f":null,"sd":[{"a":"121. CARLOS MUÑOZ SUFAN","b":"IND","c":"75","d":"1,70%","e":null,"f":"","sd":null},{"a":"122. JOSE ANDRES CORDOVA ARANEDA","b":"IND","c":"89","d":"2,01%","e":null,"f":"","sd":null}]}]},{"a":"F. POR UN CHILE JUSTO Y DESCENTRALIZADO","b":null,"c":"847","d":"19,17%","e":"5","f":"","sd":[{"a":"SUBPACTO PPD E INDEPENDIENTES","b":null,"c":"556","d":"12,58%","e":null,"f":null,"sd":[{"a":"123. DANIEL ENRIQUE CUEVAS FUENTEALBA","b":"PPD","c":"430","d":"9,73%","e":null,"f":"*","sd":null},{"a":"124. ROSSANA EVELYN ENRIQUEZ CASTILLO","b":"PPD","c":"126","d":"2,85%","e":null,"f":"","sd":null}]},{"a":"SUBPACTO PRSD E INDEPENDIENTES","b":null,"c":"171","d":"3,87%","e":null,"f":null,"sd":[{"a":"125. JAVIER BELLOY MERINO","b":"PRSD","c":"122","d":"2,76%","e":null,"f":"","sd":null},{"a":"126. JUAN JOSE TORRES PAREDES","b":"IND","c":"49","d":"1,11%","e":null,"f":"","sd":null}]},{"a":"SUBPACTO PCCH E INDEPENDIENTES","b":null,"c":"120","d":"2,72%","e":null,"f":null,"sd":[{"a":"127. MARIA ANGELICA MONARES CASTILLO","b":"PCCH","c":"120","d":"2,72%","e":null,"f":"","sd":null}]}]},{"a":"L. UNIDOS POR LA DESCENTRALIZACION","b":null,"c":"1.021","d":"23,11%","e":"5","f":"","sd":[{"a":"SUBPACTO PS E INDEPENDIENTES","b":null,"c":"285","d":"6,45%","e":null,"f":null,"sd":[{"a":"128. MARIO MORALES BURGOS","b":"PSCH","c":"148","d":"3,35%","e":null,"f":"","sd":null},{"a":"129. JOSE PINTO ALBORNOZ","b":"PSCH","c":"80","d":"1,81%","e":null,"f":"","sd":null},{"a":"130. EDWIN  VON-JENTSCHYK CRUZ","b":"PSCH","c":"57","d":"1,29%","e":null,"f":"","sd":null}]},{"a":"SUBPACTO PDC E INDEPENDIENTES","b":null,"c":"736","d":"16,66%","e":null,"f":null,"sd":[{"a":"131. MARIANO FELIPE RUIZ-ESQUIDE FIGUEROA","b":"PDC","c":"478","d":"10,82%","e":null,"f":"","sd":null},{"a":"132. TERESA DE JESUS STARK ORTEGA","b":"PDC","c":"258","d":"5,84%","e":null,"f":"*","sd":null}]}]}],"resumen":[{"a":"Válidamente Emitidos","b":null,"c":"4.418","d":"81,26%","e":null,"f":null,"sd":null},{"a":"Votos Nulos","b":null,"c":"337","d":"6,20%","e":null,"f":null,"sd":null},{"a":"Votos en Blanco","b":null,"c":"682","d":"12,54%","e":null,"f":null,"sd":null},{"a":"Total Votación","b":null,"c":"5.437","d":"100,00%","e":null,"f":null,"sd":null}],"colegioEscrutador":null,"labels":"5","mesasEscrutadas":"35","totalMesas":"35","totalMesasPorcent":"100,00%","tipoGlosaComputo":"1","mostrarGlosaNominados":true,"tipoGlosaNominados":null}