[{"c":2001001,"d":"1V","md":false},{"c":2001002,"d":"2V","md":false},{"c":2001003,"d":"3V","md":false},{"c":2001004,"d":"4V","md":false},{"c":2001005,"d":"5V","md":false},{"c":2001006,"d":"6V","md":false},{"c":2001007,"d":"7V","md":false},{"c":2001008,"d":"8V","md":false},{"c":2001009,"d":"9V","md":false},{"c":2001010,"d":"10V","md":false},{"c":2001011,"d":"11V","md":false},{"c":2001012,"d":"12V","md":false},{"c":2001013,"d":"13V","md":false},{"c":2001014,"d":"14V","md":false},{"c":2001015,"d":"15V","md":false},{"c":2001016,"d":"16V","md":false},{"c":2001017,"d":"17V","md":false},{"c":2001018,"d":"18V","md":false},{"c":2001019,"d":"19V","md":false},{"c":2001020,"d":"20V","md":false},{"c":2001021,"d":"21V","md":false},{"c":2001022,"d":"22V","md":false},{"c":2001023,"d":"23V","md":false},{"c":2001024,"d":"24V","md":false},{"c":2001025,"d":"25V","md":false},{"c":2001026,"d":"26V","md":false},{"c":2001027,"d":"27V","md":false}]