[{"c":1041001,"d":"1V","md":false},{"c":1041002,"d":"2V","md":false},{"c":1041003,"d":"3V","md":false},{"c":1041004,"d":"4V","md":false},{"c":1041005,"d":"5V","md":false},{"c":1041006,"d":"6V","md":false},{"c":1041007,"d":"7V","md":false},{"c":1041008,"d":"8V","md":false},{"c":1041009,"d":"9V","md":false},{"c":1041010,"d":"10V","md":false},{"c":1041011,"d":"11V","md":false},{"c":1041012,"d":"12V","md":false},{"c":1041013,"d":"13V","md":false},{"c":1041014,"d":"14V","md":false},{"c":1041015,"d":"15V","md":false},{"c":1041016,"d":"16V","md":false},{"c":1041017,"d":"17V","md":false},{"c":1041018,"d":"18V","md":false},{"c":1041019,"d":"19V","md":false},{"c":1041020,"d":"20V","md":false},{"c":1041021,"d":"21V","md":false}]