[{"c":1491025,"d":"25V","md":false},{"c":1491026,"d":"26V","md":false},{"c":1491027,"d":"27V","md":false},{"c":1491028,"d":"28V","md":false},{"c":1491029,"d":"29V","md":false},{"c":1491030,"d":"30V","md":false},{"c":1492244,"d":"244","md":false},{"c":1492245,"d":"245","md":false},{"c":1492246,"d":"246","md":false},{"c":1492247,"d":"247","md":false},{"c":1492248,"d":"248","md":false},{"c":1492249,"d":"249","md":false},{"c":1492250,"d":"250","md":false},{"c":1492251,"d":"251","md":false},{"c":1492252,"d":"252","md":false},{"c":1492253,"d":"253","md":false},{"c":1492254,"d":"254","md":false},{"c":1492255,"d":"255","md":false},{"c":1492256,"d":"256","md":false},{"c":1492257,"d":"257","md":false},{"c":1492258,"d":"258","md":false},{"c":1492259,"d":"259","md":false},{"c":1492260,"d":"260","md":false},{"c":1492261,"d":"261","md":false}]