[{"c":1641105,"d":"105V","md":false},{"c":1641106,"d":"106V","md":false},{"c":1641107,"d":"107V","md":false},{"c":1641108,"d":"108V","md":false},{"c":1641109,"d":"109V","md":false},{"c":1641110,"d":"110V","md":false},{"c":1641111,"d":"111V","md":false},{"c":1641112,"d":"112V","md":false},{"c":1641113,"d":"113V","md":false},{"c":1641114,"d":"114V","md":false},{"c":1641115,"d":"115V","md":false},{"c":1641116,"d":"116V","md":false},{"c":1641117,"d":"117V","md":false},{"c":1641118,"d":"118V","md":false},{"c":1641119,"d":"119V","md":false},{"c":1641120,"d":"120V","md":false},{"c":1641121,"d":"121V","md":false}]