[{"c":1581051,"d":"51V","md":false},{"c":1581052,"d":"52V","md":false},{"c":1581053,"d":"53V","md":false},{"c":1581054,"d":"54V","md":false},{"c":1581055,"d":"55V","md":false},{"c":1581056,"d":"56V","md":false},{"c":1581057,"d":"57V","md":false},{"c":1581058,"d":"58V","md":false},{"c":1581059,"d":"59V","md":false},{"c":1581060,"d":"60V","md":false},{"c":1581061,"d":"61V","md":false},{"c":1581062,"d":"62V","md":false},{"c":1581063,"d":"63V","md":false},{"c":1581064,"d":"64V","md":false},{"c":1581065,"d":"65V","md":false},{"c":1581066,"d":"66V","md":false},{"c":1581067,"d":"67V","md":false},{"c":1581068,"d":"68V","md":false},{"c":1581069,"d":"69V","md":false},{"c":1581070,"d":"70V","md":false},{"c":1581071,"d":"71V","md":false},{"c":1581072,"d":"72V","md":false},{"c":1581073,"d":"73V","md":false},{"c":1581074,"d":"74V","md":false},{"c":1581075,"d":"75V","md":false}]