[{"c":1931059,"d":"59V","md":false},{"c":1931060,"d":"60V","md":false},{"c":1931061,"d":"61V","md":false},{"c":1931062,"d":"62V","md":false},{"c":1931063,"d":"63V","md":false},{"c":1931064,"d":"64V","md":false},{"c":1931065,"d":"65V","md":false},{"c":1931066,"d":"66V","md":false},{"c":1931067,"d":"67V","md":false},{"c":1931068,"d":"68V","md":false},{"c":1931069,"d":"69V","md":false},{"c":1931070,"d":"70V","md":false},{"c":1931071,"d":"71V","md":false},{"c":1931072,"d":"72V","md":false},{"c":1931073,"d":"73V","md":false},{"c":1931074,"d":"74V","md":false},{"c":1931075,"d":"75V","md":false},{"c":1931076,"d":"76V","md":false},{"c":1931077,"d":"77V","md":false},{"c":1931078,"d":"78V","md":false},{"c":1931079,"d":"79V","md":false},{"c":1931080,"d":"80V","md":false},{"c":1931081,"d":"81V","md":false},{"c":1931082,"d":"82V","md":false},{"c":1931083,"d":"83V","md":false}]