[{"c":2410001,"d":"1M","md":false},{"c":2410002,"d":"2M","md":false},{"c":2410003,"d":"3M","md":false},{"c":2410004,"d":"4M","md":false},{"c":2410005,"d":"5M","md":false},{"c":2410006,"d":"6M","md":false},{"c":2410007,"d":"7M","md":false},{"c":2410008,"d":"8M","md":false},{"c":2410009,"d":"9M","md":false},{"c":2410010,"d":"10M","md":false},{"c":2410011,"d":"11M","md":false},{"c":2410012,"d":"12M","md":false},{"c":2410013,"d":"13M","md":false},{"c":2410014,"d":"14M","md":false},{"c":2410015,"d":"15M","md":false},{"c":2410016,"d":"16M","md":false},{"c":2410017,"d":"17M","md":false},{"c":2410018,"d":"18M","md":false},{"c":2412025,"d":"25","md":false},{"c":2412026,"d":"26","md":false},{"c":2412027,"d":"27","md":false}]